balsa/__init__.py
balsa/__version__.py
balsa/aws_cloudwatch_logs.py
balsa/balsa.py
balsa/formatter.py
balsa/get_logger.py
balsa/guihandler.py
balsa/handlers.py
balsa/py.typed
balsa/structured.py
balsa-0.21.0.dist-info/LICENSE
balsa-0.21.0.dist-info/LICENSE.txt
balsa-0.21.0.dist-info/METADATA
balsa-0.21.0.dist-info/WHEEL
balsa-0.21.0.dist-info/top_level.txt
balsa-0.21.0.dist-info/RECORD
