Metadata-Version: 2.1
Name: balsa
Version: 0.21.0
Summary: logging utility
Home-page: https://github.com/jamesabel/balsa
Download-URL: https://github.com/jamesabel/balsa/archive/master.zip
Author: James Abel
Author-email: j@abel.co
License: MIT License
Keywords: logging,utility
License-File: LICENSE
License-File: LICENSE.txt
Requires-Dist: appdirs
Requires-Dist: attrs
Requires-Dist: mttkinter
Requires-Dist: python-dateutil
Requires-Dist: yasf
Requires-Dist: tobool
